README.rst
setup.py
w20e/__init__.py
w20e.pyramidwsgi.recipe.egg-info/PKG-INFO
w20e.pyramidwsgi.recipe.egg-info/SOURCES.txt
w20e.pyramidwsgi.recipe.egg-info/dependency_links.txt
w20e.pyramidwsgi.recipe.egg-info/entry_points.txt
w20e.pyramidwsgi.recipe.egg-info/not-zip-safe
w20e.pyramidwsgi.recipe.egg-info/top_level.txt
w20e/pyramidwsgi/__init__.py
w20e/pyramidwsgi/recipe.py
w20e/pyramidwsgi/templates.py