Metadata-Version: 1.1
Name: w20e.pyramidwsgi.recipe
Version: 1.0.0
Summary: Pyramid WSGI recipe
Home-page: UNKNOWN
Author: D.A.Dokter
Author-email: dokter@w20e.com
License: UNKNOWN
Keywords: wsgi pylons pyramid
Platform: UNKNOWN
Classifier: Development Status :: 3 - Alpha
Classifier: Programming Language :: Python
Classifier: Framework :: Pylons
Classifier: Topic :: Internet :: WWW/HTTP
Classifier: Topic :: Internet :: WWW/HTTP :: WSGI :: Application
